safer_hist/__init__.py
safer_hist/__main__.py
safer_hist/genmeta.py
safer_hist/help.py
safer_hist/lsalltime.py
safer_hist/lssnaps.py
safer_hist/lsuntil.py
safer_hist/restore.py
safer_hist_pkg/__init__.py
safer_hist-0.0.2.dist-info/LICENSE
safer_hist-0.0.2.dist-info/METADATA
safer_hist-0.0.2.dist-info/WHEEL
safer_hist-0.0.2.dist-info/top_level.txt
safer_hist-0.0.2.dist-info/RECORD
