Metadata-Version: 2.1
Name: safer-hist
Version: 0.0.2
Summary: A system level API to query and manage the SAFER-STORAGE backup and storage in space in time dimensions
Home-page: https://gitlab.safer-storage.com/safer-dev-priv/nas-histo
Author: Olivier Dalle
Author-email: olivier@safer-storage.com
License: UNKNOWN
Platform: UNKNOWN
Classifier: Programming Language :: Python :: 3
Classifier: License :: OSI Approved :: European Union Public Licence 1.2 (EUPL 1.2)
Classifier: Operating System :: POSIX :: Linux
Requires-Python: >=3.7
